{
  "input": {
    "files": [],
    "opts": {
      "execute": false,
      "executeParallel": 11,
      "pdf": false,
      "tex": false,
      "typst": false,
      "docx": true,
      "md": true,
      "xml": false,
      "meca": false,
      "cff": false,
      "site": false,
      "html": false,
      "all": false,
      "doiBib": false,
      "watch": false,
      "force": false,
      "checkLinks": false,
      "strict": false,
      "ci": false,
      "maxSizeWebp": 1572864,
      "keepHost": false
    }
  },
  "exports": [
    {
      "format": "docx",
      "output": "/Users/joshuaw.kelly/Documents/GitHub/Mathematics-Notebook/exports/learning-lean-4.docx",
      "articles": [
        {
          "file": "/Users/joshuaw.kelly/Documents/GitHub/Mathematics-Notebook/foundations.md",
          "level": 1,
          "slug": "foundations"
        }
      ],
      "$file": "/Users/joshuaw.kelly/Documents/GitHub/Mathematics-Notebook/myst.yml",
      "$project": "/Users/joshuaw.kelly/Documents/GitHub/Mathematics-Notebook"
    },
    {
      "format": "md",
      "output": "/Users/joshuaw.kelly/Documents/GitHub/Mathematics-Notebook/exports/learning-lean-4.md",
      "articles": [
        {
          "file": "/Users/joshuaw.kelly/Documents/GitHub/Mathematics-Notebook/foundations.md",
          "level": 1,
          "slug": "foundations"
        }
      ],
      "$file": "/Users/joshuaw.kelly/Documents/GitHub/Mathematics-Notebook/myst.yml",
      "$project": "/Users/joshuaw.kelly/Documents/GitHub/Mathematics-Notebook"
    }
  ]
}